MANIFEST.in
README.rst
setup.py
collective/__init__.py
collective.mtrsetup.egg-info/PKG-INFO
collective.mtrsetup.egg-info/SOURCES.txt
collective.mtrsetup.egg-info/dependency_links.txt
collective.mtrsetup.egg-info/entry_points.txt
collective.mtrsetup.egg-info/namespace_packages.txt
collective.mtrsetup.egg-info/not-zip-safe
collective.mtrsetup.egg-info/requires.txt
collective.mtrsetup.egg-info/top_level.txt
collective/mtrsetup/__init__.py
collective/mtrsetup/configure.zcml
collective/mtrsetup/handler.py
collective/mtrsetup/plone3.zcml
collective/mtrsetup/plone4.zcml
collective/mtrsetup/icons/odb.png
collective/mtrsetup/icons/odc.png
collective/mtrsetup/icons/odg.png
collective/mtrsetup/icons/odp.png
collective/mtrsetup/icons/ods.png
collective/mtrsetup/icons/odt.png
collective/mtrsetup/icons/oo-empty.png
collective/mtrsetup/icons/ooo.png
collective/mtrsetup/icons/otg.png
collective/mtrsetup/icons/oth.png
collective/mtrsetup/icons/otp.png
collective/mtrsetup/icons/ots.png
collective/mtrsetup/icons/ott.png
collective/mtrsetup/profiles/default/export_steps.xml
collective/mtrsetup/profiles/default/import_steps.xml
collective/mtrsetup/profiles/example/metadata.xml
collective/mtrsetup/profiles/example/mimetypes.xml
collective/mtrsetup/tests/__init__.py
collective/mtrsetup/tests/base.py
collective/mtrsetup/tests/profile.txt
collective/mtrsetup/tests/test.zcml
collective/mtrsetup/tests/test_doctest.py
collective/mtrsetup/tests/test_profile/metadata.xml
collective/mtrsetup/tests/test_profile/mimetypes.xml
docs/HISTORY.txt