Metadata-Version: 1.0
Name: collective.mtrsetup
Version: 1.5
Summary: Extension for GenericSetup, adding support for import / export of mimetypes_registry
Home-page: https://github.com/collective/collective.mtrsetup
Author: Jonas Baumann, 4teamwork GmbH
Author-email: mailto:info@4teamwork.ch
License: GPL
Keywords: generic setup gs mimetypes registry import export
Platform: UNKNOWN
Classifier: Programming Language :: Python
